{
  "regionName": "Sheol",
  "description": "Le integre regno occultate sub le superficie.",
  "regions": [],
  "locations": {
    "bucca-de-sheol": {
      "name": "Le Bucca de Sheol",
      "description": "Le entrata ceremonial principal ab le mundo del vivos.",
      "latitude": 40.838737,
      "longitude": 14.076167,
      "elevationMeters": 1
    },
    "descenso-del-sibylla": {
      "name": "Le Descenso del Sibylla",
      "description": "Le corridor ritual per le qual le cavernas natural deveni le architectura de Sheol.",
      "latitude": 40.8479,
      "longitude": 14.0532,
      "elevationMeters": 17
    },
    "campo-del-ultime-pensamentos": {
      "name": "Le Campo del Ultime Pensamentos",
      "description": "Un campo de battalia inundate ubi le mortos repete le ultime pensamento que illes portava al morte.",
      "latitude": 40.84795,
      "longitude": 14.056381,
      "elevationMeters": 22
    },
    "cais-del-desiro": {
      "name": "Le Cais del Desiro",
      "description": "Un chantier naval submergite ubi le desiro es discargate, inventariate e consumite.",
      "latitude": 40.8291,
      "longitude": 14.0952,
      "elevationMeters": -4
    },
    "cortes-submergite": {
      "name": "Le Cortes Submergite",
      "description": "Le palatios, thermas, jardines e tribunales submergite del mortos plen de desiro.",
      "latitude": 40.817361,
      "longitude": 14.070273,
      "elevationMeters": -9
    },
    "halito-de-sheol": {
      "name": "Le Halito de Sheol",
      "description": "Le fumarolas per le qual le regno interrate exhala in le mundo del vivos.",
      "latitude": 40.827,
      "longitude": 14.139,
      "elevationMeters": 98
    },
    "costa-final": {
      "name": "Le Costa Final",
      "description": "Le ultime ripa ante le mar nigre, marcate per turres de guarda, naufragios e currentes sin retorno.",
      "latitude": 40.778259,
      "longitude": 14.088936,
      "elevationMeters": 68
    }
  },
  "routes": [
    {
      "name": "Le Sentiero del Ultime Pensamentos",
      "between": [
        "campo-del-ultime-pensamentos",
        "descenso-del-sibylla"
      ],
      "walkingTime": 10,
      "elevationChangeMeters": 5
    },
    {
      "name": "Le Via del Sibylla",
      "between": [
        "descenso-del-sibylla",
        "bucca-de-sheol"
      ],
      "walkingTime": 70,
      "elevationChangeMeters": 16
    },
    {
      "name": "Le Via del Desiro",
      "between": [
        "bucca-de-sheol",
        "cais-del-desiro"
      ],
      "walkingTime": 60,
      "elevationChangeMeters": 5
    },
    {
      "name": "Le Passage Submergite",
      "between": [
        "bucca-de-sheol",
        "cortes-submergite"
      ],
      "walkingTime": 100,
      "elevationChangeMeters": 10
    },
    {
      "name": "Le Cais del Ruinas",
      "between": [
        "cais-del-desiro",
        "cortes-submergite"
      ],
      "walkingTime": 75,
      "elevationChangeMeters": 5
    },
    {
      "name": "Le Via del Fumarolas",
      "between": [
        "cais-del-desiro",
        "halito-de-sheol"
      ],
      "walkingTime": 130,
      "elevationChangeMeters": 102
    },
    {
      "name": "Le Via del Mar Nigre",
      "between": [
        "cortes-submergite",
        "costa-final"
      ],
      "walkingTime": 150,
      "elevationChangeMeters": 77
    },
    {
      "name": "Le Sentiero del Ultime Ripa",
      "between": [
        "halito-de-sheol",
        "costa-final"
      ],
      "walkingTime": 240,
      "elevationChangeMeters": 30
    }
  ]
}
